chartbuilder/__init__.py
chartbuilder/plot.py
rwchartbuilder-1.0.7.dist-info/METADATA
rwchartbuilder-1.0.7.dist-info/WHEEL
rwchartbuilder-1.0.7.dist-info/top_level.txt
rwchartbuilder-1.0.7.dist-info/RECORD
