Metadata-Version: 2.4
Name: rwchartbuilder
Version: 1.0.7
Summary: Reusable dual-axis chart utilities for matplotlib
Author: Ryan
License: MIT
Project-URL: Homepage, https://github.com/wilksrc/chartbuilder
Project-URL: Repository, https://github.com/wilksrc/chartbuilder
Project-URL: Issues, https://github.com/wilksrc/chartbuilder/issues
Requires-Python: >=3.8
Requires-Dist: matplotlib>=3.5
Requires-Dist: pandas>=1.3
